vivdisky/__init__.py
vivdisky/exception.py
vivdisky/mdisk.py
vivdisky-0.0.7.dist-info/LICENSE
vivdisky-0.0.7.dist-info/METADATA
vivdisky-0.0.7.dist-info/WHEEL
vivdisky-0.0.7.dist-info/top_level.txt
vivdisky-0.0.7.dist-info/RECORD
