Metadata-Version: 2.1
Name: vivdisky
Version: 0.0.7
Summary: An Unofficial Asynchronous Python version of Vivdisky API wrapper
Home-page: https://github.com/TechGiron/vivdisky
Author: Tech Giron
Author-email: rahulrathee52402@gmail.com
License: MIT
Keywords: python,mdisk,mdisk wrapper,mdisk convert,earn money 
Classifier: Development Status :: 1 - Planning
Classifier: Intended Audience :: Developers
Classifier: Programming Language :: Python :: 3
Classifier: Operating System :: Unix
Classifier: Operating System :: MacOS :: MacOS X
Classifier: Operating System :: Microsoft :: Windows
License-File: LICENSE
Requires-Dist: requests
